MANIFEST.in
README
requirements.txt
setup.py
ajenti.plugin.dns_api.egg-info/PKG-INFO
ajenti.plugin.dns_api.egg-info/SOURCES.txt
ajenti.plugin.dns_api.egg-info/dependency_links.txt
ajenti.plugin.dns_api.egg-info/top_level.txt
ajenti_plugin_dns_api/.gitignore
ajenti_plugin_dns_api/README.md
ajenti_plugin_dns_api/__init__.py
ajenti_plugin_dns_api/api.py
ajenti_plugin_dns_api/main.py
ajenti_plugin_dns_api/manager.py
ajenti_plugin_dns_api/plugin.yml
ajenti_plugin_dns_api/record.py
ajenti_plugin_dns_api/requirements.txt
ajenti_plugin_dns_api/views.py
ajenti_plugin_dns_api/locale/af/LC_MESSAGES/app.js
ajenti_plugin_dns_api/locale/af/LC_MESSAGES/app.po
ajenti_plugin_dns_api/locale/ar/LC_MESSAGES/app.js
ajenti_plugin_dns_api/locale/ar/LC_MESSAGES/app.po
ajenti_plugin_dns_api/locale/be/LC_MESSAGES/app.js
ajenti_plugin_dns_api/locale/be/LC_MESSAGES/app.po
ajenti_plugin_dns_api/locale/bg/LC_MESSAGES/app.js
ajenti_plugin_dns_api/locale/bg/LC_MESSAGES/app.po
ajenti_plugin_dns_api/locale/bn/LC_MESSAGES/app.js
ajenti_plugin_dns_api/locale/bn/LC_MESSAGES/app.po
ajenti_plugin_dns_api/locale/bs/LC_MESSAGES/app.js
ajenti_plugin_dns_api/locale/bs/LC_MESSAGES/app.po
ajenti_plugin_dns_api/locale/ca/LC_MESSAGES/app.js
ajenti_plugin_dns_api/locale/ca/LC_MESSAGES/app.po
ajenti_plugin_dns_api/locale/cs/LC_MESSAGES/app.js
ajenti_plugin_dns_api/locale/cs/LC_MESSAGES/app.po
ajenti_plugin_dns_api/locale/da/LC_MESSAGES/app.js
ajenti_plugin_dns_api/locale/da/LC_MESSAGES/app.po
ajenti_plugin_dns_api/locale/de/LC_MESSAGES/app.js
ajenti_plugin_dns_api/locale/de/LC_MESSAGES/app.po
ajenti_plugin_dns_api/locale/el/LC_MESSAGES/app.js
ajenti_plugin_dns_api/locale/el/LC_MESSAGES/app.po
ajenti_plugin_dns_api/locale/en/LC_MESSAGES/app.po
ajenti_plugin_dns_api/locale/eo/LC_MESSAGES/app.js
ajenti_plugin_dns_api/locale/eo/LC_MESSAGES/app.po
ajenti_plugin_dns_api/locale/es-ES/LC_MESSAGES/app.js
ajenti_plugin_dns_api/locale/es-ES/LC_MESSAGES/app.po
ajenti_plugin_dns_api/locale/et/LC_MESSAGES/app.js
ajenti_plugin_dns_api/locale/et/LC_MESSAGES/app.po
ajenti_plugin_dns_api/locale/fa/LC_MESSAGES/app.js
ajenti_plugin_dns_api/locale/fa/LC_MESSAGES/app.po
