Metadata-Version: 2.1
Name: ajenti.plugin.dns-api
Version: 0.2
Summary: External DNS
Home-page: https://ajenti.org
Author: Arnaud Kientz
Author-email: arnaud@linuxmuster.net
Requires-Python: >=3
